[
    {
        "verb_id": 1,
        "verb": "yachten"
    },
    {
        "verb_id": 2,
        "verb": "yogisieren"
    },
    {
        "verb_id": 3,
        "verb": "yokozunieren"
    },
    {
        "verb_id": 4,
        "verb": "yorken"
    },
    {
        "verb_id": 5,
        "verb": "yorkshiren"
    },
    {
        "verb_id": 6,
        "verb": "yogurtieren"
    },
    {
        "verb_id": 7,
        "verb": "yottieren"
    },
    {
        "verb_id": 8,
        "verb": "youtuben"
    },
    {
        "verb_id": 9,
        "verb": "yowien"
    },
    {
        "verb_id": 10,
        "verb": "y-chromosomenisieren"
    }
]