[
    {
        "verb_id": 0,
        "verb": ["квакать"]
    },
    {
        "verb_id": 1,
        "verb": ["вытекать", "размачивать", "течь", "вздуваться"]
    },
    {
        "verb_id": 2,
        "verb": ["ныть", "ворчать"]
    },
    {
        "verb_id": 3,
        "verb": ["ставить поперёк"]
    },
    {
        "verb_id": 4,
        "verb": ["подтверждать", "квитировать"]
    },
    {
        "verb_id": 5,
        "verb": ["квотировать"]
    },
    {
        "verb_id": 6,
        "verb": ["болтать", "болтаться"]
    },
    {
        "verb_id": 7,
        "verb": ["мучить"]
    },
    {
        "verb_id": 8,
        "verb": ["переходить поперёк"]
    },
    {
        "verb_id": 9,
        "verb": ["выписывать квитанцию"]
    }
]
